CHANGES.rst
CONTRIBUTORS.rst
MANIFEST.in
Makefile
README.rst
bootstrap-buildout.py
buildout.cfg
setup.py
sources.cfg
versions.cfg
collective/__init__.py
collective.monitor.egg-info/PKG-INFO
collective.monitor.egg-info/SOURCES.txt
collective.monitor.egg-info/dependency_links.txt
collective.monitor.egg-info/not-zip-safe
collective.monitor.egg-info/requires.txt
collective.monitor.egg-info/top_level.txt
collective/monitor/__init__.py
collective/monitor/configure.zcml
collective/monitor/health.py
collective/monitor/monitor.py
collective/monitor/threads.py
docs/LICENSE.GPL
docs/LICENSE.txt
docs/haproxy.rst