Metadata-Version: 1.1
Name: collective.monitor
Version: 0.2.6.1
Summary: Monitoring meta package for Zope/Plone installs
Home-page: https://github.com/collective/collective.monitor
Author: Benoît Suttor
Author-email: bsuttor@imio.be
License: gpl
Keywords: Probe Plone Zope
Platform: UNKNOWN
Classifier: Environment :: Web Environment
Classifier: Programming Language :: Python
Classifier: Programming Language :: Python :: 2.7
Classifier: Framework :: Plone
Classifier: Framework :: Plone :: 4.2
Classifier: Framework :: Plone :: 4.3
